{
	"data": [
		{
			"content": "João Buscapé",
			"value": 42342342,
			"additional": [
				{
					"label": "Mãe",
					"content": "Maria"
				},
				{
					"label": "Pai",
					"content": "Fulano"
				}
			],
			"others": [
				{
					"field": "age",
					"value": 30
				},
				{
					"field": "occupation",
					"content": "CEO",
					"value": 3123213
				}
			]
		},
		{
			"content": "Beltrano",
			"value": 42342343,
			"additional": [
				{
					"label": "Mãe",
					"content": "Clotildes"
				},
				{
					"label": "Pai",
					"content": "Ciclano"
				}
			],
			"others": [
				{
					"field": "age",
					"value": 30
				},
				{
					"field": "occupation",
					"content": "Programmer",
					"value": 2342342423
				}
			]
		},
		{
			"content": "Chuck Norris",
			"value": 9999999,
			"additional": [
				{
					"label": "Mãe",
					"content": "Sra. Norris"
				},
				{
					"label": "Pai",
					"content": "Sr. Norris"
				}
			],
			"others": [
				{
					"field": "age",
					"value": 76
				},
				{
					"field": "occupation",
					"content": "Designer",
					"value": 26677777
				}
			]
		}
	],
	"pagination": {
		"total": 50,
		"per_page": 15,
		"current_page": 1
	}
}
